Metadata-Version: 2.4
Name: NEMO-floor-plans
Version: 1.0.2
Summary: Floor plans plugin for NEMO
Author-email: Atlantis Labs LLC <atlantis@atlantislabs.io>
License: MIT License
Project-URL: Homepage, https://gitlab.com/nemo-community/atlantis-labs/nemo-floor-plans
Project-URL: Changelog, https://gitlab.com/nemo-community/atlantis-labs/nemo-floor-plans/-/releases
Project-URL: Issues, https://gitlab.com/nemo-community/atlantis-labs/nemo-floor-plans/-/issues
Project-URL: CI, https://gitlab.com/nemo-community/atlantis-labs/nemo-floor-plans/-/pipelines
Keywords: NEMO
Classifier: Development Status :: 5 - Production/Stable
Classifier: Intended Audience :: Developers
Classifier: License :: OSI Approved :: MIT License
Classifier: Framework :: Django :: 4.2
Classifier: Programming Language :: Python :: 3.9
Classifier: Programming Language :: Python :: 3.10
Classifier: Programming Language :: Python :: 3.11
Classifier: Programming Language :: Python :: 3.12
Classifier: Programming Language :: Python :: 3.13
Requires-Python: >=3.9
License-File: LICENSE
Requires-Dist: django
Requires-Dist: python-dateutil
Provides-Extra: nemo-ce
Requires-Dist: NEMO-CE>=7.0.0; extra == "nemo-ce"
Provides-Extra: nemo
Requires-Dist: NEMO>=7.0.0; extra == "nemo"
Provides-Extra: nemo-sensors
Requires-Dist: nemo-sensors>=0.9.2; extra == "nemo-sensors"
Provides-Extra: dev-tools
Requires-Dist: pre-commit; extra == "dev-tools"
Requires-Dist: djlint; extra == "dev-tools"
Requires-Dist: black; extra == "dev-tools"
Dynamic: license-file
